<?xml version="1.0" ?><collection shelf="The Best Of">
<album title="The Slow Rush">
    <author>Tame Impala</author>
   <genere>Psychedelic pop</genere>
   <year>2020</year>
   <description>The fourth studio album by Australian musical project Tame Impala, released on 14 February 2020.</description>
</album>
<album title="The Miracle">
    <author>Queen</author>
   <genere>Rock</genere>
   <year>1989</year>
   <description>The thirteenth studio album by the British rock band Queen, released on 22 May 1989.</description>
</album>
<album title="Sweetener">
    <author>Ariana Grande</author>
   <genere>Pop</genere>
   <year>2018</year>
   <description>The fourth studio album by American singer Ariana Grande. It was released on August 17, 2018.</description>
</album>
<album title="Love + Fear">
    <author>Marina</author>
   <genere>Pop</genere>
   <year>2019</year>
   <description>The fourth studio album by Welsh singer Marina Diamandis and her first under the mononym Marina.</description>
</album>
<album title="AM">
    <author>Arctic Monkeys</author>
   <genere>Indie rock</genere>
   <year>2013</year>
   <description>The fifth studio album by English indie rock band Arctic Monkeys.</description>
</album>
</collection>
